rpistream/__init__.py
rpistream/camera.py
rpistream/netutils.py
rpistream/streamclient.py
rpistream/streamserver.py
rpistream-0.2.2.dist-info/METADATA
rpistream-0.2.2.dist-info/WHEEL
rpistream-0.2.2.dist-info/top_level.txt
rpistream-0.2.2.dist-info/RECORD
